[
    {
        "last_updated": 1761818139.3083067,
        "result": "In Progress",
        "odds": [
            {
                "team_name": "United Arab Emirates",
                "back": [
                    {
                        "price": "1.7",
                        "size": "447.6"
                    },
                    {
                        "price": "1.71",
                        "size": "195.3"
                    },
                    {
                        "price": "1.72",
                        "size": "1.6"
                    }
                ],
                "lay": [
                    {
                        "price": "1.74",
                        "size": "242.5"
                    },
                    {
                        "price": "1.75",
                        "size": "2.8K"
                    },
                    {
                        "price": "1.76",
                        "size": "752.1"
                    }
                ]
            },
            {
                "team_name": "Nepal",
                "back": [
                    {
                        "price": "2.26",
                        "size": "6.1"
                    },
                    {
                        "price": "2.32",
                        "size": "2.7K"
                    },
                    {
                        "price": "2.34",
                        "size": "180.3"
                    }
                ],
                "lay": [
                    {
                        "price": "2.4",
                        "size": "1.1"
                    },
                    {
                        "price": "2.42",
                        "size": "139.2"
                    },
                    {
                        "price": "2.44",
                        "size": "310.6"
                    }
                ]
            }
        ],
        "bookmarker": [
            {
                "team_name": "United Arab Emirates",
                "back": [
                    {
                        "price": "65",
                        "size": "2L"
                    },
                    {
                        "price": "66",
                        "size": "2L"
                    },
                    {
                        "price": "67",
                        "size": "2L"
                    }
                ],
                "lay": [
                    {
                        "price": "72",
                        "size": "2L"
                    },
                    {
                        "price": "73",
                        "size": "2L"
                    },
                    {
                        "price": "74",
                        "size": "2L"
                    }
                ]
            },
            {
                "team_name": "Nepal",
                "back": [],
                "lay": [
                    {
                        "price": "149",
                        "size": "50K"
                    }
                ]
            }
        ],
        "fancy": [
            {
                "name": "1st Wkt UAE",
                "no_val": "33",
                "no_size": "110",
                "yes_val": "33",
                "yes_size": "90"
            },
            {
                "name": "A Sharafu Boundaries",
                "no_val": "5",
                "no_size": "100",
                "yes_val": "6",
                "yes_size": "100"
            },
            {
                "name": "H.M.B Face By A Sharafu",
                "no_val": "36",
                "no_size": "110",
                "yes_val": "36",
                "yes_size": "90"
            },
            {
                "name": "Aryansh Sharma Boundaries",
                "no_val": "2",
                "no_size": "100",
                "yes_val": "3",
                "yes_size": "100"
            },
            {
                "name": "H.M.B Face By Aryansh Sharma",
                "no_val": "29",
                "no_size": "110",
                "yes_val": "29",
                "yes_size": "90"
            },
            {
                "name": "1st Wkt Lost To UAE Balls",
                "no_val": "40",
                "no_size": "110",
                "yes_val": "40",
                "yes_size": "90"
            },
            {
                "name": "1st Wkt Pship Boundaries UAE",
                "no_val": "4",
                "no_size": "100",
                "yes_val": "5",
                "yes_size": "100"
            },
            {
                "name": "1st Wkt Caught Out UAE @ 1",
                "no_val": "1",
                "no_size": "75",
                "yes_val": "1",
                "yes_size": "55"
            }
        ],
        "sessions": [
            {
                "name": "10 Over UAE",
                "no_val": "45",
                "no_size": "100",
                "yes_val": "46",
                "yes_size": "100"
            },
            {
                "name": "4th Over Runs Only UAE",
                "no_val": "",
                "no_size": "00",
                "yes_val": "",
                "yes_size": "00"
            },
            {
                "name": "1st Wkt UAE Run Bhav",
                "no_val": "13",
                "no_size": "8",
                "yes_val": "13",
                "yes_size": "5"
            },
            {
                "name": "A Sharafu Runs",
                "no_val": "31",
                "no_size": "100",
                "yes_val": "31",
                "yes_size": "80"
            },
            {
                "name": "A Sharafu Run Bhav",
                "no_val": "10",
                "no_size": "8",
                "yes_val": "10",
                "yes_size": "5"
            },
            {
                "name": "Aryansh Sharma Runs",
                "no_val": "19",
                "no_size": "110",
                "yes_val": "19",
                "yes_size": "90"
            },
            {
                "name": "Aryansh Sharma Run Bhav",
                "no_val": "3",
                "no_size": "9",
                "yes_val": "3",
                "yes_size": "6"
            }
        ],
        "match_id": "34898034",
        "teams": "United Arab Emirates v Nepal"
    },
    {
        "last_updated": 1761818139.7147207,
        "result": "In Progress",
        "odds": [
            {
                "team_name": "Australia W",
                "back": [
                    {
                        "price": "1.28",
                        "size": "48.2K"
                    },
                    {
                        "price": "1.29",
                        "size": "40.6K"
                    },
                    {
                        "price": "1.3",
                        "size": "6.7K"
                    }
                ],
                "lay": [
                    {
                        "price": "1.31",
                        "size": "14.3K"
                    },
                    {
                        "price": "1.32",
                        "size": "13.2K"
                    },
                    {
                        "price": "1.33",
                        "size": "15.1K"
                    }
                ]
            },
            {
                "team_name": "India W",
                "back": [
                    {
                        "price": "4",
                        "size": "5.0K"
                    },
                    {
                        "price": "4.1",
                        "size": "3.9K"
                    },
                    {
                        "price": "4.2",
                        "size": "4.9K"
                    }
                ],
                "lay": [
                    {
                        "price": "4.3",
                        "size": "7.7"
                    },
                    {
                        "price": "4.4",
                        "size": "2.1K"
                    },
                    {
                        "price": "4.5",
                        "size": "11.6K"
                    }
                ]
            }
        ],
        "bookmarker": [
            {
                "team_name": "Australia W",
                "back": [
                    {
                        "price": "28",
                        "size": "10L"
                    },
                    {
                        "price": "29",
                        "size": "10L"
                    },
                    {
                        "price": "30",
                        "size": "10L"
                    }
                ],
                "lay": [
                    {
                        "price": "32",
                        "size": "10L"
                    },
                    {
                        "price": "33",
                        "size": "10L"
                    },
                    {
                        "price": "34",
                        "size": "10L"
                    }
                ]
            },
            {
                "team_name": "India W",
                "back": [],
                "lay": [
                    {
                        "price": "333",
                        "size": "2.5L"
                    }
                ]
            }
        ],
        "fancy": [
            {
                "name": "1st Wkt AUSW",
                "no_val": "58",
                "no_size": "115",
                "yes_val": "58",
                "yes_size": "95"
            },
            {
                "name": "1st 2 Wkt AUSW",
                "no_val": "106",
                "no_size": "115",
                "yes_val": "106",
                "yes_size": "95"
            },
            {
                "name": "1st 3 Wkt AUSW",
                "no_val": "155",
                "no_size": "110",
                "yes_val": "155",
                "yes_size": "90"
            },
            {
                "name": "1st 4 Wkt AUSW",
                "no_val": "203",
                "no_size": "110",
                "yes_val": "203",
                "yes_size": "90"
            },
            {
                "name": "P Litchfield Boundaries",
                "no_val": "9",
                "no_size": "100",
                "yes_val": "10",
                "yes_size": "100"
            },
            {
                "name": "H.M.B Face By P Litchfield",
                "no_val": "46",
                "no_size": "110",
                "yes_val": "46",
                "yes_size": "90"
            },
            {
                "name": "A Healy Boundaries",
                "no_val": "4",
                "no_size": "100",
                "yes_val": "5",
                "yes_size": "100"
            },
            {
                "name": "H.M.B Face By A Healy",
                "no_val": "38",
                "no_size": "120",
                "yes_val": "38",
                "yes_size": "100"
            },
            {
                "name": "1st Wkt Lost To AUSW Balls",
                "no_val": "",
                "no_size": "00",
                "yes_val": "",
                "yes_size": "00"
            },
            {
                "name": "1st Wkt Pship Boundaries AUSW",
                "no_val": "9",
                "no_size": "100",
                "yes_val": "10",
                "yes_size": "100"
            },
            {
                "name": "1st Wkt Caught Out AUSW @ 1",
                "no_val": "1",
                "no_size": "70",
                "yes_val": "1",
                "yes_size": "50"
            }
        ],
        "sessions": [
            {
                "name": "1st Innings 10 Overs Line",
                "no_val": "58",
                "no_size": "29.0K",
                "yes_val": "59",
                "yes_size": "18.6K"
            },
            {
                "name": "1st Innings 50 Overs Line",
                "no_val": "321",
                "no_size": "1.3K",
                "yes_val": "322",
                "yes_size": "6.4K"
            },
            {
                "name": "15 Over AUSW",
                "no_val": "84",
                "no_size": "100",
                "yes_val": "86",
                "yes_size": "100"
            },
            {
                "name": "10 Over AUSW 1",
                "no_val": "58",
                "no_size": "100",
                "yes_val": "59",
                "yes_size": "100"
            },
            {
                "name": "10 Over AUSW",
                "no_val": "58",
                "no_size": "100",
                "yes_val": "59",
                "yes_size": "100"
            },
            {
                "name": "5.3 Over AUSW",
                "no_val": "28",
                "no_size": "100",
                "yes_val": "29",
                "yes_size": "100"
            },
            {
                "name": "6 Over AUSW",
                "no_val": "",
                "no_size": "00",
                "yes_val": "",
                "yes_size": "00"
            },
            {
                "name": "50 Over AUSW 1",
                "no_val": "319",
                "no_size": "100",
                "yes_val": "322",
                "yes_size": "100"
            },
            {
                "name": "50 Over AUSW",
                "no_val": "318",
                "no_size": "100",
                "yes_val": "321",
                "yes_size": "100"
            },
            {
                "name": "7th Over Runs Only AUSW",
                "no_val": "6",
                "no_size": "100",
                "yes_val": "7",
                "yes_size": "100"
            },
            {
                "name": "1st Wkt AUSW Run Bhav",
                "no_val": "26",
                "no_size": "6",
                "yes_val": "26",
                "yes_size": "3"
            },
            {
                "name": "P Litchfield Runs",
                "no_val": "51",
                "no_size": "110",
                "yes_val": "51",
                "yes_size": "90"
            },
            {
                "name": "P Litchfield Run Bhav",
                "no_val": "18",
                "no_size": "6",
                "yes_val": "18",
                "yes_size": "3"
            },
            {
                "name": "A Healy Runs",
                "no_val": "36",
                "no_size": "110",
                "yes_val": "36",
                "yes_size": "90"
            },
            {
                "name": "A Healy Run Bhav",
                "no_val": "6",
                "no_size": "7",
                "yes_val": "6",
                "yes_size": "4"
            },
            {
                "name": "5.1 Ball Run AUSW",
                "no_val": "26",
                "no_size": "120",
                "yes_val": "26",
                "yes_size": "80"
            },
            {
                "name": "5.2 Ball Run AUSW",
                "no_val": "",
                "no_size": "00",
                "yes_val": "",
                "yes_size": "00"
            },
            {
                "name": "5.3 Ball Run AUSW",
                "no_val": "",
                "no_size": "00",
                "yes_val": "",
                "yes_size": "00"
            },
            {
                "name": "5.4 Ball Run AUSW",
                "no_val": "",
                "no_size": "00",
                "yes_val": "",
                "yes_size": "00"
            },
            {
                "name": "5.5 Ball Run AUSW",
                "no_val": "",
                "no_size": "00",
                "yes_val": "",
                "yes_size": "00"
            },
            {
                "name": "5.6 Ball Run AUSW",
                "no_val": "",
                "no_size": "00",
                "yes_val": "",
                "yes_size": "00"
            }
        ],
        "match_id": "34886842",
        "teams": "Australia W v India W"
    },
    {
        "last_updated": 1761818128.6247644,
        "result": "In Progress",
        "odds": [
            {
                "team_name": "The Draw",
                "back": [],
                "lay": []
            },
            {
                "team_name": "Western Australia",
                "back": [],
                "lay": []
            },
            {
                "team_name": "South Australia",
                "back": [],
                "lay": []
            }
        ],
        "bookmarker": [],
        "fancy": [
            {
                "name": "5th Wkt SA (2)",
                "no_val": "307",
                "no_size": "110",
                "yes_val": "307",
                "yes_size": "90"
            },
            {
                "name": "J Lehmann Boundaries (2)",
                "no_val": "10",
                "no_size": "100",
                "yes_val": "11",
                "yes_size": "100"
            },
            {
                "name": "N McAndrew Boundaries (2)",
                "no_val": "",
                "no_size": "00",
                "yes_val": "",
                "yes_size": "00"
            },
            {
                "name": "5th WKT Pship Boundaries SA (2)",
                "no_val": "",
                "no_size": "00",
                "yes_val": "",
                "yes_size": "00"
            },
            {
                "name": "5th WKT Caught Out SA @ 1 (2)",
                "no_val": "1",
                "no_size": "70",
                "yes_val": "1",
                "yes_size": "55"
            }
        ],
        "sessions": [
            {
                "name": "J Lehmann Runs (2)",
                "no_val": "58",
                "no_size": "110",
                "yes_val": "58",
                "yes_size": "90"
            },
            {
                "name": "N McAndrew Runs (2)",
                "no_val": "",
                "no_size": "00",
                "yes_val": "",
                "yes_size": "00"
            }
        ],
        "match_id": "34867872",
        "teams": "Western Australia v South Australia"
    }
]